{
    "status": "ok",
    "totalResults": 1852,
    "articles": [
        {
            "source": {
                "id": null,
                "name": "Yahoo Entertainment"
            },
            "author": "Amy Skorheim",
            "title": "Black Friday Apple deals 2024: The best Apple sales on iPads, AirPods, Apple Watches and MacBooks",
            "description": "Apple devices have a few things in common: they’re well-designed, solidly built and easily connect with one another. But chances are, if it bears the Apple logo, it’s not cheap. That’s why promos like Black Friday are always worth checking out if you’re in th…",
            "url": "https://consent.yahoo.com/v2/collectConsent?sessionId=1_cc-session_5b50f93c-f2e5-4f39-87c2-8667512a5599",
            "urlToImage": null,
            "publishedAt": "2024-11-19T16:51:43Z",
            "content": "If you click 'Accept all', we and our partners, including 237 who are part of the IAB Transparency &amp; Consent Framework, will also store and/or access information on a device (in other words, use … [+678 chars]"
        },
        {
            "source": {
                "id": null,
                "name": "Yahoo Entertainment"
            },
            "author": "Jeff Dunn,Valentina Palladino,Amy Skorheim",
            "title": "The 40 Black Friday tech deals worth shopping from Amazon, Walmart, Apple, Anker and others",
            "description": "November is in full swing, which means Black Friday is right around the corner. But the days in which you had to wait for Black Friday proper to get good deals have long been behind us. The holiday shopping season is effectively the entire month of November n…",
            "url": "https://consent.yahoo.com/v2/collectConsent?sessionId=1_cc-session_b68b9c5c-07ab-4b44-bfe2-40dec39c65aa",
            "urlToImage": null,
            "publishedAt": "2024-11-19T14:51:03Z",
            "content": "If you click 'Accept all', we and our partners, including 237 who are part of the IAB Transparency &amp; Consent Framework, will also store and/or access information on a device (in other words, use … [+678 chars]"
        },
        {
            "source": {
                "id": null,
                "name": "Yahoo Entertainment"
            },
            "author": "Kris Holt",
            "title": "The 2024 Roku Ultra drops to $80 in this Black Friday deal",
            "description": "While pretty much every TV is a smart TV these days, you might still want a dedicated streaming box to do the heavy lifting — or maybe you'd like to have one for a projector. There a number of Black Friday deals\r\n on streaming devices, including the latest Ro…",
            "url": "https://consent.yahoo.com/v2/collectConsent?sessionId=1_cc-session_c172ad2c-c9eb-4365-9494-f49eaa2f5022",
            "urlToImage": null,
            "publishedAt": "2024-11-19T18:15:28Z",
            "content": "If you click 'Accept all', we and our partners, including 237 who are part of the IAB Transparency &amp; Consent Framework, will also store and/or access information on a device (in other words, use … [+678 chars]"
        },
        {
            "source": {
                "id": "wired",
                "name": "Wired"
            },
            "author": "Simon Hill",
            "title": "25 Best Early Black Friday Deals of 2024 to Shop Right Now",
            "description": "It doesn’t officially arrive until November 29, but the Black Friday deals have already begun. Shop steep discounts on gear tested and approved by our editors.",
            "url": "https://www.wired.com/story/early-black-friday-deals-2024-1/",
            "urlToImage": "https://media.wired.com/photos/6733e0b69870c92e316a2a79/191:100/w_1280,c_limit/03-early-black-friday-deals.png",
            "publishedAt": "2024-11-19T17:00:42Z",
            "content": "Black Friday is the big day for retailers slashing prices to kick off the holiday shopping season and clear out their 2024 stock. But you dont have to wait to carve the Thanksgiving turkey and watch … [+13681 chars]"
        }
    ]
}